bleuio_lib/__init__.py
bleuio_lib/bleuio_funcs.py
bleuio_lib/exceptions.py
bleuio_tests/__init__.py
bleuio_tests/test_bleuio_funcs.py
tests/__init__.py
tests/test_bleuio_funcs.py
bleuio-1.7.2.dist-info/LICENSE.txt
bleuio-1.7.2.dist-info/METADATA
bleuio-1.7.2.dist-info/WHEEL
bleuio-1.7.2.dist-info/top_level.txt
bleuio-1.7.2.dist-info/RECORD
