Metadata-Version: 2.1
Name: bleuio
Version: 1.7.2
Summary: Library for using the bleuio dongle.
Home-page: https://smart-sensor-devices-ab.github.io/ssd005-manual/
Author: Smart Sensor Devices
Author-email: smartzenzor@gmail.com
License: MIT
Platform: UNKNOWN
Requires-Python: >=3.5
Requires-Dist: pyserial
